know_py_shell-0.1.2.dist-info/METADATA
know_py_shell-0.1.2.dist-info/WHEEL
know_py_shell.cpython-37m-darwin.so
know_py_shell-0.1.2.dist-info/RECORD
