Metadata-Version: 2.1
Name: know-py-shell
Version: 0.1.2
Classifier: Programming Language :: Python
Summary: Python extension for know-thy-shell.info
Author: Marius Seritan <github@winding-lines.com>
Author-Email: Marius Seritan <github@winding-lines.com>
License: MIT
